conway_pygame/__init__.py
conway_pygame/__main__.py
conway_pygame/games.py
conway_pygame-0.3.0.dist-info/LICENSE
conway_pygame-0.3.0.dist-info/METADATA
conway_pygame-0.3.0.dist-info/WHEEL
conway_pygame-0.3.0.dist-info/entry_points.txt
conway_pygame-0.3.0.dist-info/top_level.txt
conway_pygame-0.3.0.dist-info/RECORD
