Metadata-Version: 2.1
Name: conway-pygame
Version: 0.3.0
Summary: Conway's Game of Life in Pygame
Home-page: https://gitlab.com/frague59/conway
Author-email: François GUÉRIN <frague59@gmail.com>
License: UNKNOWN
Project-URL: homepage, https://gitlab.com/frague59/conway
Project-URL: repository, https://gitlab.com/frague59/conway
Keywords: conway,game,life,pygame
Platform: UNKNOWN
Classifier: Development Status :: 4 - Beta
Classifier: Environment :: X11 Applications
Classifier: Intended Audience :: Developers
Classifier: License :: OSI Approved :: MIT License
Classifier: Natural Language :: English
Classifier: Operating System :: OS Independent
Classifier: Programming Language :: Python :: 3
Classifier: Programming Language :: Python :: 3.9
Classifier: Programming Language :: Python :: 3.10
Classifier: Topic :: Games/Entertainment
Classifier: Topic :: Games/Entertainment :: Simulation
Classifier: Topic :: Software Development :: Libraries :: pygame
Classifier: Topic :: Multimedia :: Graphics :: Viewers
License-File: LICENSE
Requires-Dist: pygame (<3.0.0,>=2.1.2)
Requires-Dist: click (<9.0.0,>=8.0.0)
